{
	"id": "3g7z0cQBAT7fKzA",
	"json": "{\"id\":\"3g7z0cQBAT7fKzA\",\"url\":\"https://qavanin.ir/Law/TreeText/?IDS=1981140593166842457\",\"loadedUrl\":\"https://qavanin.ir/Law/TreeText/?IDS=1981140593166842457\",\"uniqueKey\":\"https://qavanin.ir/Law/TreeText?IDS=1981140593166842457\",\"method\":\"GET\",\"noRetry\":false,\"retryCount\":0,\"errorMessages\":[],\"headers\":{},\"userData\":{\"__crawlee\":{\"state\":4}},\"handledAt\":\"2024-12-21T13:18:14.940Z\"}",
	"method": "GET",
	"orderNo": null,
	"retryCount": 0,
	"uniqueKey": "https://qavanin.ir/Law/TreeText?IDS=1981140593166842457",
	"url": "https://qavanin.ir/Law/TreeText/?IDS=1981140593166842457"
}