{
	"id": "5V7yVKTsq6zYvPK",
	"json": "{\"id\":\"5V7yVKTsq6zYvPK\",\"url\":\"https://qavanin.ir/Law/TreeText/?IDS=10218960852321362588\",\"uniqueKey\":\"https://qavanin.ir/Law/TreeText?IDS=10218960852321362588\",\"method\":\"GET\",\"noRetry\":false,\"retryCount\":0,\"errorMessages\":[],\"headers\":{},\"userData\":{}}",
	"method": "GET",
	"orderNo": 1734782193360,
	"retryCount": 0,
	"uniqueKey": "https://qavanin.ir/Law/TreeText?IDS=10218960852321362588",
	"url": "https://qavanin.ir/Law/TreeText/?IDS=10218960852321362588"
}