{
	"id": "DNelWlIIL7rhCx7",
	"json": "{\"id\":\"DNelWlIIL7rhCx7\",\"url\":\"https://qavanin.ir/Law/TreeText/?IDS=13743186594909506257\",\"uniqueKey\":\"https://qavanin.ir/Law/TreeText?IDS=13743186594909506257\",\"method\":\"GET\",\"noRetry\":false,\"retryCount\":0,\"errorMessages\":[],\"headers\":{},\"userData\":{}}",
	"method": "GET",
	"orderNo": 1734782193594,
	"retryCount": 0,
	"uniqueKey": "https://qavanin.ir/Law/TreeText?IDS=13743186594909506257",
	"url": "https://qavanin.ir/Law/TreeText/?IDS=13743186594909506257"
}