{
	"id": "FIbh6zgHiPIypyb",
	"json": "{\"id\":\"FIbh6zgHiPIypyb\",\"url\":\"https://qavanin.ir/Law/TreeText/?IDS=11646297386230802736\",\"uniqueKey\":\"https://qavanin.ir/Law/TreeText?IDS=11646297386230802736\",\"method\":\"GET\",\"noRetry\":false,\"retryCount\":0,\"errorMessages\":[],\"headers\":{},\"userData\":{}}",
	"method": "GET",
	"orderNo": 1734782193750,
	"retryCount": 0,
	"uniqueKey": "https://qavanin.ir/Law/TreeText?IDS=11646297386230802736",
	"url": "https://qavanin.ir/Law/TreeText/?IDS=11646297386230802736"
}