{
	"id": "jg4aqtWXHwjjotf",
	"json": "{\"id\":\"jg4aqtWXHwjjotf\",\"url\":\"https://qavanin.ir/Law/TreeText/?IDS=2253316108232102986\",\"loadedUrl\":\"https://qavanin.ir/Law/TreeText/?IDS=2253316108232102986\",\"uniqueKey\":\"https://qavanin.ir/Law/TreeText?IDS=2253316108232102986\",\"method\":\"GET\",\"noRetry\":false,\"retryCount\":0,\"errorMessages\":[],\"headers\":{},\"userData\":{\"__crawlee\":{\"state\":4}},\"handledAt\":\"2024-12-21T13:15:56.676Z\"}",
	"method": "GET",
	"orderNo": null,
	"retryCount": 0,
	"uniqueKey": "https://qavanin.ir/Law/TreeText?IDS=2253316108232102986",
	"url": "https://qavanin.ir/Law/TreeText/?IDS=2253316108232102986"
}