{
	"id": "oxxrj3hSrtBWEua",
	"json": "{\"id\":\"oxxrj3hSrtBWEua\",\"url\":\"https://qavanin.ir/Law/TreeText/?IDS=3357549860671290630\",\"loadedUrl\":\"https://qavanin.ir/Law/TreeText/?IDS=3357549860671290630\",\"uniqueKey\":\"https://qavanin.ir/Law/TreeText?IDS=3357549860671290630\",\"method\":\"GET\",\"noRetry\":false,\"retryCount\":0,\"errorMessages\":[],\"headers\":{},\"userData\":{\"__crawlee\":{\"state\":4}},\"handledAt\":\"2024-12-21T13:09:56.298Z\"}",
	"method": "GET",
	"orderNo": null,
	"retryCount": 0,
	"uniqueKey": "https://qavanin.ir/Law/TreeText?IDS=3357549860671290630",
	"url": "https://qavanin.ir/Law/TreeText/?IDS=3357549860671290630"
}