{
	"id": "qtM7Cgzu812q7lG",
	"json": "{\"id\":\"qtM7Cgzu812q7lG\",\"url\":\"https://qavanin.ir/Law/TreeText/?IDS=8410272202784622236\",\"uniqueKey\":\"https://qavanin.ir/Law/TreeText?IDS=8410272202784622236\",\"method\":\"GET\",\"noRetry\":false,\"retryCount\":0,\"errorMessages\":[],\"headers\":{},\"userData\":{}}",
	"method": "GET",
	"orderNo": 1734782193832,
	"retryCount": 0,
	"uniqueKey": "https://qavanin.ir/Law/TreeText?IDS=8410272202784622236",
	"url": "https://qavanin.ir/Law/TreeText/?IDS=8410272202784622236"
}