{
	"id": "R4nyJo8RIjoFDgz",
	"json": "{\"id\":\"R4nyJo8RIjoFDgz\",\"url\":\"https://qavanin.ir/Law/TreeText/?IDS=5908841227365087992\",\"uniqueKey\":\"https://qavanin.ir/Law/TreeText?IDS=5908841227365087992\",\"method\":\"GET\",\"noRetry\":false,\"retryCount\":0,\"errorMessages\":[],\"headers\":{},\"userData\":{}}",
	"method": "GET",
	"orderNo": 1734782193846,
	"retryCount": 0,
	"uniqueKey": "https://qavanin.ir/Law/TreeText?IDS=5908841227365087992",
	"url": "https://qavanin.ir/Law/TreeText/?IDS=5908841227365087992"
}