{
	"id": "r87slc0MBydA174",
	"json": "{\"id\":\"r87slc0MBydA174\",\"url\":\"https://qavanin.ir/Law/TreeText/?IDS=3080468224439774943\",\"loadedUrl\":\"https://qavanin.ir/Law/TreeText/?IDS=3080468224439774943\",\"uniqueKey\":\"https://qavanin.ir/Law/TreeText?IDS=3080468224439774943\",\"method\":\"GET\",\"noRetry\":false,\"retryCount\":0,\"errorMessages\":[],\"headers\":{},\"userData\":{\"__crawlee\":{\"state\":4}},\"handledAt\":\"2024-12-21T13:18:33.720Z\"}",
	"method": "GET",
	"orderNo": null,
	"retryCount": 0,
	"uniqueKey": "https://qavanin.ir/Law/TreeText?IDS=3080468224439774943",
	"url": "https://qavanin.ir/Law/TreeText/?IDS=3080468224439774943"
}