{
	"id": "sugNUdfFTq15UZD",
	"json": "{\"id\":\"sugNUdfFTq15UZD\",\"url\":\"https://ehghagh.com/مهدیس-گودرزی/بازداشت-موقت-بیان-توضیحاتی-در-خصوص-تبصره-ماده-237-قانون-آیین-دادرسی-کیفری-و-مواد-238-و-255-و-256-این-قانون\",\"loadedUrl\":\"https://ehghagh.com/%D9%85%D9%87%D8%AF%DB%8C%D8%B3-%DA%AF%D9%88%D8%AF%D8%B1%D8%B2%DB%8C/%D8%A8%D8%A7%D8%B2%D8%AF%D8%A7%D8%B4%D8%AA-%D9%85%D9%88%D9%82%D8%AA-%D8%A8%DB%8C%D8%A7%D9%86-%D8%AA%D9%88%D8%B6%DB%8C%D8%AD%D8%A7%D8%AA%DB%8C-%D8%AF%D8%B1-%D8%AE%D8%B5%D9%88%D8%B5-%D8%AA%D8%A8%D8%B5%D8%B1%D9%87-%D9%85%D8%A7%D8%AF%D9%87-237-%D9%82%D8%A7%D9%86%D9%88%D9%86-%D8%A2%DB%8C%DB%8C%D9%86-%D8%AF%D8%A7%D8%AF%D8%B1%D8%B3%DB%8C-%DA%A9%DB%8C%D9%81%D8%B1%DB%8C-%D9%88-%D9%85%D9%88%D8%A7%D8%AF-238-%D9%88-255-%D9%88-256-%D8%A7%DB%8C%D9%86-%D9%82%D8%A7%D9%86%D9%88%D9%86\",\"uniqueKey\":\"https://ehghagh.com/%D9%85%D9%87%D8%AF%DB%8C%D8%B3-%DA%AF%D9%88%D8%AF%D8%B1%D8%B2%DB%8C/%D8%A8%D8%A7%D8%B2%D8%AF%D8%A7%D8%B4%D8%AA-%D9%85%D9%88%D9%82%D8%AA-%D8%A8%DB%8C%D8%A7%D9%86-%D8%AA%D9%88%D8%B6%DB%8C%D8%AD%D8%A7%D8%AA%DB%8C-%D8%AF%D8%B1-%D8%AE%D8%B5%D9%88%D8%B5-%D8%AA%D8%A8%D8%B5%D8%B1%D9%87-%D9%85%D8%A7%D8%AF%D9%87-237-%D9%82%D8%A7%D9%86%D9%88%D9%86-%D8%A2%DB%8C%DB%8C%D9%86-%D8%AF%D8%A7%D8%AF%D8%B1%D8%B3%DB%8C-%DA%A9%DB%8C%D9%81%D8%B1%DB%8C-%D9%88-%D9%85%D9%88%D8%A7%D8%AF-238-%D9%88-255-%D9%88-256-%D8%A7%DB%8C%D9%86-%D9%82%D8%A7%D9%86%D9%88%D9%86\",\"method\":\"GET\",\"noRetry\":false,\"retryCount\":0,\"errorMessages\":[],\"headers\":{},\"userData\":{\"__crawlee\":{\"state\":4}},\"handledAt\":\"2024-12-14T15:33:54.761Z\"}",
	"method": "GET",
	"orderNo": null,
	"retryCount": 0,
	"uniqueKey": "https://ehghagh.com/%D9%85%D9%87%D8%AF%DB%8C%D8%B3-%DA%AF%D9%88%D8%AF%D8%B1%D8%B2%DB%8C/%D8%A8%D8%A7%D8%B2%D8%AF%D8%A7%D8%B4%D8%AA-%D9%85%D9%88%D9%82%D8%AA-%D8%A8%DB%8C%D8%A7%D9%86-%D8%AA%D9%88%D8%B6%DB%8C%D8%AD%D8%A7%D8%AA%DB%8C-%D8%AF%D8%B1-%D8%AE%D8%B5%D9%88%D8%B5-%D8%AA%D8%A8%D8%B5%D8%B1%D9%87-%D9%85%D8%A7%D8%AF%D9%87-237-%D9%82%D8%A7%D9%86%D9%88%D9%86-%D8%A2%DB%8C%DB%8C%D9%86-%D8%AF%D8%A7%D8%AF%D8%B1%D8%B3%DB%8C-%DA%A9%DB%8C%D9%81%D8%B1%DB%8C-%D9%88-%D9%85%D9%88%D8%A7%D8%AF-238-%D9%88-255-%D9%88-256-%D8%A7%DB%8C%D9%86-%D9%82%D8%A7%D9%86%D9%88%D9%86",
	"url": "https://ehghagh.com/مهدیس-گودرزی/بازداشت-موقت-بیان-توضیحاتی-در-خصوص-تبصره-ماده-237-قانون-آیین-دادرسی-کیفری-و-مواد-238-و-255-و-256-این-قانون"
}