{
	"id": "YdSY1IV9HwJQxI4",
	"json": "{\"id\":\"YdSY1IV9HwJQxI4\",\"url\":\"https://qavanin.ir/Law/TreeText/?IDS=11399188639913308800\",\"uniqueKey\":\"https://qavanin.ir/Law/TreeText?IDS=11399188639913308800\",\"method\":\"GET\",\"noRetry\":false,\"retryCount\":0,\"errorMessages\":[],\"headers\":{},\"userData\":{}}",
	"method": "GET",
	"orderNo": 1734782193460,
	"retryCount": 0,
	"uniqueKey": "https://qavanin.ir/Law/TreeText?IDS=11399188639913308800",
	"url": "https://qavanin.ir/Law/TreeText/?IDS=11399188639913308800"
}